poetry_release/__init__.py
poetry_release/command.py
poetry_release/config.py
poetry_release/exception.py
poetry_release/executor.py
poetry_release/git.py
poetry_release/plugin.py
poetry_release/replace.py
poetry_release/version.py
poetry_release-0.3.1.dist-info/entry_points.txt
poetry_release-0.3.1.dist-info/LICENSE
poetry_release-0.3.1.dist-info/WHEEL
poetry_release-0.3.1.dist-info/METADATA
poetry_release-0.3.1.dist-info/RECORD
