Metadata-Version: 2.1
Name: poetry-release
Version: 0.3.1
Summary: Plugin for release management in projects based on Poetry
Home-page: https://github.com/topenkoff/poetry-release
License: MIT
Author: Denis Kayshev
Author-email: topenkoff@gmail.com
Requires-Python: >=3.7,<4.0
Classifier: License :: OSI Approved :: MIT License
Classifier: Programming Language :: Python :: 3
Classifier: Programming Language :: Python :: 3.7
Classifier: Programming Language :: Python :: 3.8
Classifier: Programming Language :: Python :: 3.9
Classifier: Programming Language :: Python :: 3.10
Requires-Dist: poetry (>=1.2.0,<2.0.0)
Project-URL: Repository, https://github.com/topenkoff/poetry-release
